<?xml version='1.1' encoding='UTF-8'?>
<com.cloudbees.plugins.credentials.SystemCredentialsProvider plugin="credentials@1189.vf61b_a_5e2f62e">
  <domainCredentialsMap class="hudson.util.CopyOnWriteMap$Hash">
    <entry>
      <com.cloudbees.plugins.credentials.domains.Domain>
        <specifications/>
      </com.cloudbees.plugins.credentials.domains.Domain>
      <java.util.concurrent.CopyOnWriteArrayList>
        <org.jenkinsci.plugins.plaincredentials.impl.StringCredentialsImpl plugin="plain-credentials@139.ved2b_9cf7587b">
          <scope>GLOBAL</scope>
          <id>c6955fc7-d01d-48cc-8a45-dc42e9f76475</id>
          <description></description>
          <secret>{AQAAABAAAAAwzUjZ2D0MrdfbyHVKrCw3f/HKH6fXa+Vz0XepbZwBIkrn9DDtlp9tQfICIIyy6f8LuUh+3bnpUP2EbGJlcNSd4w==}</secret>
        </org.jenkinsci.plugins.plaincredentials.impl.StringCredentialsImpl>
      </java.util.concurrent.CopyOnWriteArrayList>
    </entry>
  </domainCredentialsMap>
</com.cloudbees.plugins.credentials.SystemCredentialsProvider>